autohooks/__version__.py
autohooks/api/__init__.py
autohooks/api/git.py
autohooks/api/path.py
autohooks/cli/__init__.py
autohooks/cli/activate.py
autohooks/cli/check.py
autohooks/cli/plugins.py
autohooks/config.py
autohooks/hooks.py
autohooks/precommit/__init__.py
autohooks/precommit/run.py
autohooks/precommit/template
autohooks/py.typed
autohooks/settings.py
autohooks/template.py
autohooks/terminal.py
autohooks/utils.py
autohooks/version.py
autohooks-25.11.0.dist-info/METADATA
autohooks-25.11.0.dist-info/WHEEL
autohooks-25.11.0.dist-info/entry_points.txt
autohooks-25.11.0.dist-info/licenses/LICENSE
autohooks-25.11.0.dist-info/RECORD
