Metadata-Version: 2.4
Name: autohooks
Version: 25.11.0
Summary: Library for managing git hooks
License: GPL-3.0-or-later
License-File: LICENSE
Keywords: git,formatting,linting,hooks
Author: Greenbone AG
Author-email: info@greenbone.net
Requires-Python: >=3.9,<4.0
Classifier: Development Status :: 5 - Production/Stable
Classifier: Environment :: Console
Classifier: Intended Audience :: Developers
Classifier: Intended Audience :: System Administrators
Classifier: License :: OSI Approved :: GNU General Public License v3 or later (GPLv3+)
Classifier: Operating System :: OS Independent
Classifier: Programming Language :: Python :: 3
Classifier: Programming Language :: Python :: 3.9
Classifier: Programming Language :: Python :: 3.10
Classifier: Programming Language :: Python :: 3.11
Classifier: Programming Language :: Python :: 3.12
Classifier: Programming Language :: Python :: 3.13
Classifier: Programming Language :: Python :: 3.14
Classifier: Topic :: Software Development :: Libraries :: Python Modules
Classifier: Topic :: Software Development :: Version Control :: Git
Requires-Dist: pontos (>=22.8.0)
Requires-Dist: rich (>=12.5.1)
Requires-Dist: shtab (>=1.7.0)
Requires-Dist: tomlkit (>=0.5.11)
Project-URL: Documentation, https://greenbone.github.io/autohooks/
Project-URL: Homepage, https://github.com/greenbone/autohooks/
Project-URL: Repository, https://github.com/greenbone/autohooks/
